3xsd
3xsd.conf
MANIFEST.in
README.3fs
README.md
_3xsd.py
setup.py
3xsd.egg-info/PKG-INFO
3xsd.egg-info/SOURCES.txt
3xsd.egg-info/dependency_links.txt
3xsd.egg-info/requires.txt
3xsd.egg-info/top_level.txt