Metadata-Version: 1.1
Name: 3xsd
Version: 0.0.26
Summary: 3xsd is a native epoll server serving TCP/UDP connections, a high performance static web server, a failover dns server, a http-based distributed file server, a load-balance proxy-cache server, and a warp-drive server. Written in python, take the full power of multi-cores.
Home-page: https://github.com/zihuaye/3xsd
Author: Zihua Ye
Author-email: zihua.ye@gmail.com zihua.ye@qq.com
License: GPLv2
Platform: UNKNOWN
Classifier: Topic :: Internet :: WWW/HTTP :: HTTP Servers
Classifier: Topic :: Internet :: Name Service (DNS)
Classifier: Topic :: Internet :: Proxy Servers
Classifier: Topic :: System :: Filesystems
Classifier: License :: OSI Approved :: GNU General Public License v2 (GPLv2)
